spacyemoticon/__init__.py
spacyemoticon/about.py
spacyemoticon/emoticons.py
spacyemoticon-1.0.2.dist-info/METADATA
spacyemoticon-1.0.2.dist-info/RECORD
spacyemoticon-1.0.2.dist-info/WHEEL
spacyemoticon-1.0.2.dist-info/top_level.txt
